{
  "编程网站": {
    "编码工具": {
      "Visual Studio Code": {
        "url": "https://code.visualstudio.com/",
        "description": "微软开发的轻量级代码编辑器",
        "icon": "https://files.codelife.cc/website/visual-studio-code.svg"
      },
      "GitHub": {
        "url": "https://github.com/",
        "description": "全球最大的代码托管平台",
        "icon": "https://files.codelife.cc/website/github.svg"
      },
      "Gitee": {
        "url": "https://gitee.com/",
        "description": "中国本土的代码托管平台",
        "icon": "https://files.codelife.cc/website/gitee.svg"
      },
      "MarsCode": {
        "url": "https://marscode.com.cn/",
        "description": "豆包旗下的智能编程工具",
        "icon": "https://lf-cdn.marscode.com.cn/obj/marscode-cn-release/marscode-icon.png"
      },
      "CodePen": {
        "url": "https://codepen.io/",
        "description": "前端代码在线编辑器",
        "icon": "https://files.codelife.cc/website/codepen.svg"
      },
      "JSFiddle": {
        "url": "https://jsfiddle.net/",
        "description": "在线JavaScript代码测试工具",
        "icon": "https://files.codelife.cc/website/jsfiddle.png"
      },
      "StackBlitz": {
        "url": "https://stackblitz.com/",
        "description": "在线IDE，支持多种框架",
        "icon": "https://files.codelife.cc/website/stackblitz.svg"
      },
      "GitLab": {
        "url": "https://gitlab.com/",
        "description": "开源的代码托管平台",
        "icon": "https://files.codelife.cc/website/gitlab.svg"
      },
      "Bitbucket": {
        "url": "https://bitbucket.org/",
        "description": "Atlassian旗下的代码托管平台",
        "icon": "https://files.codelife.cc/website/bitbucket.svg"
      },
      "Docker": {
        "url": "https://www.docker.com/",
        "description": "容器化应用平台",
        "icon": "https://files.codelife.cc/website/docker.svg"
      },
      "Travis CI": {
        "url": "https://travis-ci.org/",
        "description": "持续集成工具",
        "icon": "https://files.codelife.cc/website/travis-ci.svg"
      },
      "Postman": {
        "url": "https://www.postman.com/",
        "description": "API开发测试工具",
        "icon": "https://files.codelife.cc/website/postman.svg"
      },
      "Insomnia": {
        "url": "https://insomnia.rest/",
        "description": "REST API客户端",
        "icon": "https://files.codelife.cc/website/insomnia.svg"
      },
      "Apifox": {
        "url": "https://www.apifox.cn/",
        "description": "API一体化协作平台",
        "icon": "https://files.codelife.cc/icons/www.apifox.cn.svg"
      },
      "Eolink": {
        "url": "https://www.eolink.com/",
        "description": "API管理平台",
        "icon": "https://files.codelife.cc/icons/www.eolink.com.svg"
      },
      "ShowDoc": {
        "url": "https://www.showdoc.com.cn/",
        "description": "在线API文档工具",
        "icon": "https://files.codelife.cc/icons/www.showdoc.com.cn.svg"
      },
      "语雀": {
        "url": "https://www.yuque.com/",
        "description": "专业的云端知识库",
        "icon": "https://files.codelife.cc/icons/www.yuque.com.svg"
      },
      "Notion": {
        "url": "https://www.notion.so/",
        "description": "一体化工作空间",
        "icon": "https://files.codelife.cc/website/notion.svg"
      },
      "Figma": {
        "url": "https://www.figma.com/",
        "description": "协作式设计工具",
        "icon": "https://files.codelife.cc/website/figma.svg"
      },
      "Sketch": {
        "url": "https://www.sketch.com/",
        "description": "矢量图形设计工具",
        "icon": "https://files.codelife.cc/website/sketch.svg"
      },
      "Canva可画": {
        "url": "https://www.canva.cn/",
        "description": "在线设计工具平台",
        "icon": "https://files.codelife.cc/website/canva.svg"
      },
      "ProcessOn": {
        "url": "https://www.processon.com/",
        "description": "在线流程图制作",
        "icon": "https://files.codelife.cc/icons/www.processon.com.svg"
      }
    },
    "后端": {
      "MyBatis": {
        "url": "https://mybatis.org/mybatis-3/",
        "description": "Java持久层框架",
        "icon": "https://files.codelife.cc/user-website-icon/20220803/J_G1ipNrekOYJSmTCACZ99269.png"
      },
      "MyBatis-Plus": {
        "url": "https://baomidou.com/",
        "description": "MyBatis增强工具",
        "icon": "https://files.codelife.cc/icons/20bacf68b2efe5b2.png"
      },
      "Maven": {
        "url": "https://maven.apache.org/",
        "description": "Java项目管理工具",
        "icon": "https://files.codelife.cc/website/5b3110634c14a60c5612d3e1.png"
      },
      "MySQL": {
        "url": "https://dev.mysql.com/",
        "description": "开源关系型数据库",
        "icon": "https://files.codelife.cc/website/5f4386f4aa121b0c2ac69e22.png"
      },
      "Spring": {
        "url": "https://spring.io/",
        "description": "Java企业级开发框架",
        "icon": "https://files.codelife.cc/website/5b307dd14c14a60c5612d29d.png"
      },
      "AspectJ": {
        "url": "http://www.eclipse.org/aspectj/",
        "description": "面向切面编程框架",
        "icon": "https://files.codelife.cc/user-website-icon/20220814/wRMKMVFZ1rcjFhTxnLOeM9848.png"
      },
      "Kotlin 语言中文站": {
        "url": "https://www.kotlincn.net",
        "description": "现代化编程语言",
        "icon": "https://www.kotlincn.net/assets/images/apple-touch-icon-72x72.png"
      },
      "Repository": {
        "url": "https://mvnrepository.com/",
        "description": "Maven中央仓库",
        "icon": "https://files.codelife.cc/website/5acb1d9017fa1105a20f93ec.png"
      },
      "Redis": {
        "url": "https://redis.io/",
        "description": "内存数据结构存储",
        "icon": "https://files.codelife.cc/website/redis.svg"
      },
      "MongoDB": {
        "url": "https://www.mongodb.com/",
        "description": "文档型数据库",
        "icon": "https://files.codelife.cc/website/mongodb.svg"
      },
      "PostgreSQL": {
        "url": "https://www.postgresql.org/",
        "description": "高级开源关系型数据库",
        "icon": "https://files.codelife.cc/website/postgresql.svg"
      },
      "Elasticsearch": {
        "url": "https://www.elastic.co/",
        "description": "分布式搜索引擎",
        "icon": "https://files.codelife.cc/website/elasticsearch.svg"
      },
      "Apache Kafka": {
        "url": "https://kafka.apache.org/",
        "description": "分布式流处理平台",
        "icon": "https://files.codelife.cc/website/kafka.svg"
      },
      "Apache ZooKeeper": {
        "url": "https://zookeeper.apache.org/",
        "description": "分布式协调服务",
        "icon": "https://files.codelife.cc/website/zookeeper.svg"
      },
      "Apache Dubbo": {
        "url": "https://dubbo.apache.org/",
        "description": "高性能RPC框架",
        "icon": "https://files.codelife.cc/website/dubbo.svg"
      },
      "Nacos": {
        "url": "https://nacos.io/",
        "description": "动态服务发现配置管理",
        "icon": "https://files.codelife.cc/website/nacos.svg"
      },
      "RabbitMQ": {
        "url": "https://www.rabbitmq.com/",
        "description": "消息队列中间件",
        "icon": "https://files.codelife.cc/website/rabbitmq.svg"
      },
      "Apache RocketMQ": {
        "url": "https://rocketmq.apache.org/",
        "description": "分布式消息中间件",
        "icon": "https://files.codelife.cc/website/rocketmq.svg"
      }
    },
    "前端": {
      "React": {
        "url": "https://react.dev/",
        "description": "用于构建用户界面的JavaScript库",
        "icon": "https://files.codelife.cc/website/react.svg"
      },
      "Vue.js": {
        "url": "https://vuejs.org/",
        "description": "渐进式JavaScript框架",
        "icon": "https://files.codelife.cc/website/vue.svg"
      },
      "Angular": {
        "url": "https://angular.io/",
        "description": "Google开发的前端框架",
        "icon": "https://files.codelife.cc/website/angular.svg"
      },
      "TypeScript": {
        "url": "https://www.typescriptlang.org/",
        "description": "JavaScript的超集，添加了类型系统",
        "icon": "https://files.codelife.cc/website/typescript.svg"
      },
      "Webpack": {
        "url": "https://webpack.js.org/",
        "description": "现代JavaScript应用程序的静态模块打包工具",
        "icon": "https://files.codelife.cc/website/webpack.svg"
      },
      "Vite": {
        "url": "https://vitejs.dev/",
        "description": "下一代前端构建工具",
        "icon": "https://files.codelife.cc/website/vite.svg"
      },
      "Next.js": {
        "url": "https://nextjs.org/",
        "description": "React全栈框架",
        "icon": "https://files.codelife.cc/website/nextjs.svg"
      },
      "Nuxt.js": {
        "url": "https://nuxt.com/",
        "description": "Vue.js的全栈框架",
        "icon": "https://files.codelife.cc/website/nuxt.svg"
      },
      "Tailwind CSS": {
        "url": "https://tailwindcss.com/",
        "description": "实用优先的CSS框架",
        "icon": "https://files.codelife.cc/website/tailwindcss.svg"
      },
      "Bootstrap": {
        "url": "https://getbootstrap.com/",
        "description": "流行的响应式前端框架",
        "icon": "https://files.codelife.cc/website/bootstrap.svg"
      }
    },
    "第三方对接": {},
    "学习资源": {},
    "论坛区域": {}
  },
  "工具网站": {
    "PDF转换": {
      "iLovePDF": {
        "url": "https://www.ilovepdf.com/",
        "description": "完全免费的PDF文件在线管理工具",
        "icon": "https://www.xiaozhongjishu.com/wp-content/uploads/2020/11/iLovePDF.png"
      },
      "PDF转换器": {
        "url": "https://www.pdf2go.com/zh",
        "description": "在线PDF转换器",
        "icon": "https://www.xiaozhongjishu.com/wp-content/uploads/2020/11/pdf2go.png"
      },
      "PDF Eagle": {
        "url": "https://cn.pdf eagle.com/",
        "description": "专业PDF编辑器",
        "icon": "https://www.xiaozhongjishu.com/wp-content/uploads/2020/11/PDFEagle.png"
      },
      "Smallpdf": {
        "url": "https://smallpdf.com/cn",
        "description": "在线PDF工具集合",
        "icon": "https://www.xiaozhongjishu.com/wp-content/uploads/2020/11/smallpdf.png"
      },
      "PDF24 Tools": {
        "url": "https://tools.pdf24.org/zh/",
        "description": "免费且易于使用的在线PDF工具",
        "icon": "https://www.xiaozhongjishu.com/wp-content/uploads/2020/11/pdf24.png"
      },
      "CleverPDF": {
        "url": "https://www.cleverpdf.com/",
        "description": "44个强大的PDF在线工具",
        "icon": "https://www.xiaozhongjishu.com/wp-content/uploads/2020/11/cleverpdf.png"
      },
      "超级PDF": {
        "url": "https://xpdf.net/",
        "description": "强大易用的在线PDF处理工具",
        "icon": "https://www.xiaozhongjishu.com/wp-content/uploads/2020/11/xpdf.png"
      },
      "PDF派": {
        "url": "https://www.pdfpai.com/",
        "description": "20个好用的PDF在线工具",
        "icon": "https://www.xiaozhongjishu.com/wp-content/uploads/2020/11/pdfpai.png"
      }
    },
    "数码相关": {
      "鲁大师天梯榜": {
        "url": "https://www.ludashi.com/tianti",
        "description": "手机、PC硬件性能排行榜",
        "icon": "https://www.xiaozhongjishu.com/wp-content/uploads/2020/11/ludashi.png"
      },
      "SiliconCat": {
        "url": "https://www.siliconcat.com/",
        "description": "CPU、GPU、手机SOC性能排行榜",
        "icon": "https://www.xiaozhongjishu.com/wp-content/uploads/2020/11/siliconcat.png"
      },
      "显卡性能天梯图": {
        "url": "https://www.mydrivers.com/zhuanti/tianti/gpu/",
        "description": "显卡性能排行榜",
        "icon": "https://www.xiaozhongjishu.com/wp-content/uploads/2020/11/mydrivers.png"
      },
      "手机性能排行榜": {
        "url": "https://www.phonearena.com/phones/benchmarks",
        "description": "手机性能跑分排行榜",
        "icon": "https://www.xiaozhongjishu.com/wp-content/uploads/2020/11/phonearena.png"
      },
      "快科技天梯榜": {
        "url": "https://www.mydrivers.com/zhuanti/tianti/",
        "description": "CPU、显卡、手机性能排行榜",
        "icon": "https://www.xiaozhongjishu.com/wp-content/uploads/2020/11/mydrivers.png"
      },
      "纳米AI搜索": {
        "url": "https://bot.n.cn/",
        "description": "360AI搜索，AI智能答案引擎",
        "icon": "https://www.xiaozhongjishu.com/wp-content/uploads/2024/04/1744285564-n.cn.png"
      },
      "苹果产品参数中心": {
        "url": "https://www.xiaozhongjishu.com/apple/",
        "description": "Apple产品型号查询",
        "icon": "https://www.xiaozhongjishu.com/wp-content/uploads/2022/08/9da9f-www.onlineit.cn.png"
      },
      "NotebookCheck": {
        "url": "https://www.notebookcheck.net/Mobile-Processors-Benchmark-List.2436.0.html",
        "description": "桌面及手机CPU排行榜",
        "icon": "https://www.xiaozhongjishu.com/wp-content/uploads/2021/05/mobile-processos.png"
      }
    }
  }
}